efault/__init__.py
efault/version.py
efault-1.0.0.data/data/LICENSE
efault-1.0.0.dist-info/LICENSE
efault-1.0.0.dist-info/METADATA
efault-1.0.0.dist-info/WHEEL
efault-1.0.0.dist-info/top_level.txt
efault-1.0.0.dist-info/RECORD
